kandinskylib/__init__.py
kandinskylib/kandinskylib.py
kandinskylib-0.1.4.dist-info/LICENSE.lic
kandinskylib-0.1.4.dist-info/METADATA
kandinskylib-0.1.4.dist-info/WHEEL
kandinskylib-0.1.4.dist-info/top_level.txt
kandinskylib-0.1.4.dist-info/RECORD
