Metadata-Version: 2.1
Name: kandinskylib
Version: 0.1.4
Summary: A library for working with Kandinsky AI image generator API
Home-page: https://github.com/Read1dno/kandinskylib
Author: Read1dno
Author-email: ef8ser@gmail.com
Keywords: kandinsky,ai,image generation,api
Classifier: Development Status :: 3 - Alpha
Classifier: Intended Audience :: Developers
Classifier: Topic :: Software Development :: Libraries
Classifier: License :: OSI Approved :: MIT License
Classifier: Programming Language :: Python :: 3.10
Requires-Python: >=3.6, <4
License-File: LICENSE.lic
Requires-Dist: requests
Requires-Dist: pillow
